master.v
module master(
    output reg scl,
    output reg sda,
    input clk,
    input beg
);

parameter Default = 3'b000, Start = 3'b001, Send_Add = 3'b010;
parameter Stretch = 3'b011, Send_Reg = 3'b100, Restart = 3'b101, Listen = 3'b110;

// Restart no es realmente un estado sino una flag para reutilizar los demás estados


// Si el clock es de 12MHz: 1 periodo es de 8.33e-8 y se necesitan
// 120 ciclos completos para hacer un periodo de una señal de 100 kHz

parameter Ns = 60; // N de ciclos de reloj equivalenes a 1 semiciclo
parameter Delay = 5; // Delay para evitar stop o start cuando no es
reg [2:0] state;
reg [$clog2(20*Ns):0] counter;
reg [2:0] st_prev;

initial begin
  state <= Default;
  st_prev <= Default;
  counter <= 0;
end

always @(posedge clk) begin
  case (state)
    Default: if (beg) state <= Start;
             else begin 
                state <= Default;
                scl <= 1;
                sda <= 1;
                counter <= 0;
             end
    Start : 
            if (st_prev == Default) begin
              if (counter == Ns) begin
                sda <= 0;
                scl <= 1;
                counter <= counter + 1;
              end else if (counter == 2*Ns)begin
                sda <= 0;
                scl <= 0;
                counter <= counter + 1;
              end else if (counter == 3*Ns)begin
                sda <= 1;
                scl <= 0;
                counter = 0;
                state <= Send_Add;
                st_prev <= Default;
              end else counter <= counter +1;
            end
            // Restart
            else if (st_prev == Send_Reg) begin
              if (counter == Ns) begin
                sda <= 1;
                scl <= 1;
                counter <= counter + 1;
              end else if (counter == 2*Ns)begin
                sda <= 0;
                scl <= 1;
                counter <= counter + 1;
              end else if (counter == 3*Ns)begin
                sda <= 0;
                scl <= 0;
                counter <= counter +1;
              end else if (counter == 3*Ns +Delay)begin
                sda <= 1;
                scl <= 0;
                counter = 0;
                state <= Send_Add;
                st_prev <= Restart;
              end else counter <= counter +1;
            end 
    Send_Add:
            if (st_prev == Default) begin
              // Impares
              if (counter%(Ns)==0 && counter%(2*Ns)!= 0)begin
                scl <= ~scl;
                counter <= counter + 1;
              end
              // Pares
              else if (counter%(2*Ns)== 0)begin
                scl <= 0;
                counter <= counter + 1;
              
              end else if (counter == 2*Ns +Delay)begin
                sda <= 1;
                counter <= counter + 1;
              end else if (counter == 4*Ns +Delay)begin
                sda <= 0;
                counter <= counter + 1;
              end else if (counter == 6*Ns +Delay)begin
                sda <= 1;
                counter <= counter + 1;
              end else if (counter == 8*Ns +Delay)begin
                sda <= 0;
                counter <= counter + 1;
              end else if (counter == 10*Ns +Delay)begin
                sda <= 0;
                counter <= counter + 1;
              end else if (counter == 12*Ns +Delay)begin
                sda <= 0;
                counter <= counter + 1;
                // Write
              end else if (counter == 14*Ns +Delay)begin
                sda <= 0;
                counter <= counter + 1;
                // Ack
              end else if (counter == 16*Ns +Delay)begin
                sda <= 1'bz;
                counter <= counter +1;
              end else if (counter == 18*Ns +Delay)begin
                sda <= 1'b1;
                counter <= 0;
                state <= Stretch;
                st_prev <= Send_Add;
              end else counter <= counter +1; 
            end else if (st_prev == Restart) begin
              // Impares
              if (counter%(Ns)==0 && counter%(2*Ns)!= 0)begin
                scl <= ~scl;
                counter <= counter + 1;
              end
              // Pares
              else if (counter%(2*Ns)== 0)begin
                scl <= 0;
                counter <= counter + 1;
              
              end else if (counter == 2*Ns +Delay)begin
                sda <= 1;
                counter <= counter + 1;
              end else if (counter == 4*Ns +Delay)begin
                sda <= 0;
                counter <= counter + 1;
              end else if (counter == 6*Ns +Delay)begin
                sda <= 1;
                counter <= counter + 1;
              end else if (counter == 8*Ns +Delay)begin
                sda <= 0;
                counter <= counter + 1;
              end else if (counter == 10*Ns +Delay)begin
                sda <= 0;
                counter <= counter + 1;
              end else if (counter == 12*Ns +Delay)begin
                sda <= 0;
                counter <= counter + 1;
                // Read
              end else if (counter == 14*Ns +Delay)begin              
                sda <= 1;
                counter <= counter + 1;
                // Ack
              end else if (counter == 16*Ns +Delay)begin
                sda <= 1'bz;
                counter <= counter +1;
              end else if (counter == 18*Ns +Delay)begin
                sda <= 1'b0;
                counter <= 0;
                state <= Stretch;
                st_prev <= Restart;
              end else counter <= counter +1; 
            end
    Stretch:
            if (st_prev == Send_Add)begin
              if (counter == Ns)begin
                sda <= 1'b0;
                scl <= 0;
                counter <= 0;
                state <= Send_Reg;
              end else counter <= counter +1;
            end else if (st_prev == Send_Reg)begin
              if (counter == Ns)begin
                sda <= 1'b1;
                scl <= 0;
                counter <= 0;
                state <= Start;
                st_prev <= Send_Reg;
              end else counter <= counter +1;  
            end else if (st_prev == Restart)begin
              if (counter == Ns)begin
                sda <= 1'b0;
                scl <= 0;
                counter <= 0;
                state <= Listen;
              end else counter <= counter +1;
            end
    Send_Reg:
            // Impares
             if (counter%(Ns)==0 && counter%(2*Ns)!= 0)begin
              scl <= ~scl;
              counter <= counter + 1;
             end
            // Pares
             else if (counter%(2*Ns)== 0)begin
              scl <= 0;
              counter <= counter + 1;
           // Ack
             end else if (counter == 16*Ns +Delay)begin
              sda <= 1'bz;
              counter <= counter +1;
             end else if (counter == 18*Ns +Delay)begin
              sda <= 1'b0;
              counter <= 0;
              state <= Stretch;
              st_prev <= Send_Reg;
            end else counter <= counter +1; 
          
  endcase
end

endmodule

tb_master.v
`timescale 1ns/1ps //(unidad de tiempo)/(resolución)
`include "master.v"

module tb_master ();

wire scl;
wire sda;

reg clk = 0;
reg beg = 1'b0;

always #41.667 clk = ~clk; // se simula un clock de 12MHz

initial begin
    #416.67 beg = 1'b1;
end

master master(
    .clk(clk),
    .beg(beg),
    .scl(scl),
    .sda(sda)
);

initial begin
    $dumpfile("tb_master.vcd");
    $dumpvars(-1,master);
    #400000 $finish;
end

endmodule

build/tb_master.vcd
$date
	Sun Jun 29 23:10:27 2025
$end
$version
	Icarus Verilog
$end
$timescale
	1ps
$end
$scope module tb_master $end
$scope module master $end
$var wire 1 ! beg $end
$var wire 1 " clk $end
$var parameter 3 # Default $end
$var parameter 32 $ Delay $end
$var parameter 3 % Listen $end
$var parameter 32 & Ns $end
$var parameter 3 ' Restart $end
$var parameter 3 ( Send_Add $end
$var parameter 3 ) Send_Reg $end
$var parameter 3 * Start $end
$var parameter 3 + Stretch $end
$var reg 12 , counter [11:0] $end
$var reg 1 - scl $end
$var reg 1 . sda $end
$var reg 3 / st_prev [2:0] $end
$var reg 3 0 state [2:0] $end
$upscope $end
$upscope $end
$enddefinitions $end
$comment Show the parameter values. $end
$dumpall
b11 +
b1 *
b100 )
b10 (
b101 '
b111100 &
b110 %
b101 $
b0 #
$end
#0
$dumpvars
b0 0
b0 /
x.
x-
b0 ,
0"
0!
$end
#41667
1.
1-
1"
#83334
0"
#125001
1"
#166668
0"
#208335
1"
#250002
0"
#291669
1"
#333336
0"
#375003
1"
#416670
0"
1!
#458337
b1 0
1"
#500004
0"
#541671
b1 ,
1"
#583338
0"
#625005
b10 ,
1"
#666672
0"
#708339
b11 ,
1"
#750006
0"
#791673
b100 ,
1"
#833340
0"
#875007
b101 ,
1"
#916674
0"
#958341
b110 ,
1"
#1000008
0"
#1041675
b111 ,
1"
#1083342
0"
#1125009
b1000 ,
1"
#1166676
0"
#1208343
b1001 ,
1"
#1250010
0"
#1291677
b1010 ,
1"
#1333344
0"
#1375011
b1011 ,
1"
#1416678
0"
#1458345
b1100 ,
1"
#1500012
0"
#1541679
b1101 ,
1"
#1583346
0"
#1625013
b1110 ,
1"
#1666680
0"
#1708347
b1111 ,
1"
#1750014
0"
#1791681
b10000 ,
1"
#1833348
0"
#1875015
b10001 ,
1"
#1916682
0"
#1958349
b10010 ,
1"
#2000016
0"
#2041683
b10011 ,
1"
#2083350
0"
#2125017
b10100 ,
1"
#2166684
0"
#2208351
b10101 ,
1"
#2250018
0"
#2291685
b10110 ,
1"
#2333352
0"
#2375019
b10111 ,
1"
#2416686
0"
#2458353
b11000 ,
1"
#2500020
0"
#2541687
b11001 ,
1"
#2583354
0"
#2625021
b11010 ,
1"
#2666688
0"
#2708355
b11011 ,
1"
#2750022
0"
#2791689
b11100 ,
1"
#2833356
0"
#2875023
b11101 ,
1"
#2916690
0"
#2958357
b11110 ,
1"
#3000024
0"
#3041691
b11111 ,
1"
#3083358
0"
#3125025
b100000 ,
1"
#3166692
0"
#3208359
b100001 ,
1"
#3250026
0"
#3291693
b100010 ,
1"
#3333360
0"
#3375027
b100011 ,
1"
#3416694
0"
#3458361
b100100 ,
1"
#3500028
0"
#3541695
b100101 ,
1"
#3583362
0"
#3625029
b100110 ,
1"
#3666696
0"
#3708363
b100111 ,
1"
#3750030
0"
#3791697
b101000 ,
1"
#3833364
0"
#3875031
b101001 ,
1"
#3916698
0"
#3958365
b101010 ,
1"
#4000032
0"
#4041699
b101011 ,
1"
#4083366
0"
#4125033
b101100 ,
1"
#4166700
0"
#4208367
b101101 ,
1"
#4250034
0"
#4291701
b101110 ,
1"
#4333368
0"
#4375035
b101111 ,
1"
#4416702
0"
#4458369
b110000 ,
1"
#4500036
0"
#4541703
b110001 ,
1"
#4583370
0"
#4625037
b110010 ,
1"
#4666704
0"
#4708371
b110011 ,
1"
#4750038
0"
#4791705
b110100 ,
1"
#4833372
0"
#4875039
b110101 ,
1"
#4916706
0"
#4958373
b110110 ,
1"
#5000040
0"
#5041707
b110111 ,
1"
#5083374
0"
#5125041
b111000 ,
1"
#5166708
0"
#5208375
b111001 ,
1"
#5250042
0"
#5291709
b111010 ,
1"
#5333376
0"
#5375043
b111011 ,
1"
#5416710
0"
#5458377
b111100 ,
1"
#5500044
0"
#5541711
b111101 ,
0.
1"
#5583378
0"
#5625045
b111110 ,
1"
#5666712
0"
#5708379
b111111 ,
1"
#5750046
0"
#5791713
b1000000 ,
1"
#5833380
0"
#5875047
b1000001 ,
1"
#5916714
0"
#5958381
b1000010 ,
1"
#6000048
0"
#6041715
b1000011 ,
1"
#6083382
0"
#6125049
b1000100 ,
1"
#6166716
0"
#6208383
b1000101 ,
1"
#6250050
0"
#6291717
b1000110 ,
1"
#6333384
0"
#6375051
b1000111 ,
1"
#6416718
0"
#6458385
b1001000 ,
1"
#6500052
0"
#6541719
b1001001 ,
1"
#6583386
0"
#6625053
b1001010 ,
1"
#6666720
0"
#6708387
b1001011 ,
1"
#6750054
0"
#6791721
b1001100 ,
1"
#6833388
0"
#6875055
b1001101 ,
1"
#6916722
0"
#6958389
b1001110 ,
1"
#7000056
0"
#7041723
b1001111 ,
1"
#7083390
0"
#7125057
b1010000 ,
1"
#7166724
0"
#7208391
b1010001 ,
1"
#7250058
0"
#7291725
b1010010 ,
1"
#7333392
0"
#7375059
b1010011 ,
1"
#7416726
0"
#7458393
b1010100 ,
1"
#7500060
0"
#7541727
b1010101 ,
1"
#7583394
0"
#7625061
b1010110 ,
1"
#7666728
0"
#7708395
b1010111 ,
1"
#7750062
0"
#7791729
b1011000 ,
1"
#7833396
0"
#7875063
b1011001 ,
1"
#7916730
0"
#7958397
b1011010 ,
1"
#8000064
0"
#8041731
b1011011 ,
1"
#8083398
0"
#8125065
b1011100 ,
1"
#8166732
0"
#8208399
b1011101 ,
1"
#8250066
0"
#8291733
b1011110 ,
1"
#8333400
0"
#8375067
b1011111 ,
1"
#8416734
0"
#8458401
b1100000 ,
1"
#8500068
0"
#8541735
b1100001 ,
1"
#8583402
0"
#8625069
b1100010 ,
1"
#8666736
0"
#8708403
b1100011 ,
1"
#8750070
0"
#8791737
b1100100 ,
1"
#8833404
0"
#8875071
b1100101 ,
1"
#8916738
0"
#8958405
b1100110 ,
1"
#9000072
0"
#9041739
b1100111 ,
1"
#9083406
0"
#9125073
b1101000 ,
1"
#9166740
0"
#9208407
b1101001 ,
1"
#9250074
0"
#9291741
b1101010 ,
1"
#9333408
0"
#9375075
b1101011 ,
1"
#9416742
0"
#9458409
b1101100 ,
1"
#9500076
0"
#9541743
b1101101 ,
1"
#9583410
0"
#9625077
b1101110 ,
1"
#9666744
0"
#9708411
b1101111 ,
1"
#9750078
0"
#9791745
b1110000 ,
1"
#9833412
0"
#9875079
b1110001 ,
1"
#9916746
0"
#9958413
b1110010 ,
1"
#10000080
0"
#10041747
b1110011 ,
1"
#10083414
0"
#10125081
b1110100 ,
1"
#10166748
0"
#10208415
b1110101 ,
1"
#10250082
0"
#10291749
b1110110 ,
1"
#10333416
0"
#10375083
b1110111 ,
1"
#10416750
0"
#10458417
b1111000 ,
1"
#10500084
0"
#10541751
b1111001 ,
0-
1"
#10583418
0"
#10625085
b1111010 ,
1"
#10666752
0"
#10708419
b1111011 ,
1"
#10750086
0"
#10791753
b1111100 ,
1"
#10833420
0"
#10875087
b1111101 ,
1"
#10916754
0"
#10958421
b1111110 ,
1"
#11000088
0"
#11041755
b1111111 ,
1"
#11083422
0"
#11125089
b10000000 ,
1"
#11166756
0"
#11208423
b10000001 ,
1"
#11250090
0"
#11291757
b10000010 ,
1"
#11333424
0"
#11375091
b10000011 ,
1"
#11416758
0"
#11458425
b10000100 ,
1"
#11500092
0"
#11541759
b10000101 ,
1"
#11583426
0"
#11625093
b10000110 ,
1"
#11666760
0"
#11708427
b10000111 ,
1"
#11750094
0"
#11791761
b10001000 ,
1"
#11833428
0"
#11875095
b10001001 ,
1"
#11916762
0"
#11958429
b10001010 ,
1"
#12000096
0"
#12041763
b10001011 ,
1"
#12083430
0"
#12125097
b10001100 ,
1"
#12166764
0"
#12208431
b10001101 ,
1"
#12250098
0"
#12291765
b10001110 ,
1"
#12333432
0"
#12375099
b10001111 ,
1"
#12416766
0"
#12458433
b10010000 ,
1"
#12500100
0"
#12541767
b10010001 ,
1"
#12583434
0"
#12625101
b10010010 ,
1"
#12666768
0"
#12708435
b10010011 ,
1"
#12750102
0"
#12791769
b10010100 ,
1"
#12833436
0"
#12875103
b10010101 ,
1"
#12916770
0"
#12958437
b10010110 ,
1"
#13000104
0"
#13041771
b10010111 ,
1"
#13083438
0"
#13125105
b10011000 ,
1"
#13166772
0"
#13208439
b10011001 ,
1"
#13250106
0"
#13291773
b10011010 ,
1"
#13333440
0"
#13375107
b10011011 ,
1"
#13416774
0"
#13458441
b10011100 ,
1"
#13500108
0"
#13541775
b10011101 ,
1"
#13583442
0"
#13625109
b10011110 ,
1"
#13666776
0"
#13708443
b10011111 ,
1"
#13750110
0"
#13791777
b10100000 ,
1"
#13833444
0"
#13875111
b10100001 ,
1"
#13916778
0"
#13958445
b10100010 ,
1"
#14000112
0"
#14041779
b10100011 ,
1"
#14083446
0"
#14125113
b10100100 ,
1"
#14166780
0"
#14208447
b10100101 ,
1"
#14250114
0"
#14291781
b10100110 ,
1"
#14333448
0"
#14375115
b10100111 ,
1"
#14416782
0"
#14458449
b10101000 ,
1"
#14500116
0"
#14541783
b10101001 ,
1"
#14583450
0"
#14625117
b10101010 ,
1"
#14666784
0"
#14708451
b10101011 ,
1"
#14750118
0"
#14791785
b10101100 ,
1"
#14833452
0"
#14875119
b10101101 ,
1"
#14916786
0"
#14958453
b10101110 ,
1"
#15000120
0"
#15041787
b10101111 ,
1"
#15083454
0"
#15125121
b10110000 ,
1"
#15166788
0"
#15208455
b10110001 ,
1"
#15250122
0"
#15291789
b10110010 ,
1"
#15333456
0"
#15375123
b10110011 ,
1"
#15416790
0"
#15458457
b10110100 ,
1"
#15500124
0"
#15541791
b10 0
1.
b0 ,
1"
#15583458
0"
#15625125
b1 ,
1"
#15666792
0"
#15708459
b10 ,
1"
#15750126
0"
#15791793
b11 ,
1"
#15833460
0"
#15875127
b100 ,
1"
#15916794
0"
#15958461
b101 ,
1"
#16000128
0"
#16041795
b110 ,
1"
#16083462
0"
#16125129
b111 ,
1"
#16166796
0"
#16208463
b1000 ,
1"
#16250130
0"
#16291797
b1001 ,
1"
#16333464
0"
#16375131
b1010 ,
1"
#16416798
0"
#16458465
b1011 ,
1"
#16500132
0"
#16541799
b1100 ,
1"
#16583466
0"
#16625133
b1101 ,
1"
#16666800
0"
#16708467
b1110 ,
1"
#16750134
0"
#16791801
b1111 ,
1"
#16833468
0"
#16875135
b10000 ,
1"
#16916802
0"
#16958469
b10001 ,
1"
#17000136
0"
#17041803
b10010 ,
1"
#17083470
0"
#17125137
b10011 ,
1"
#17166804
0"
#17208471
b10100 ,
1"
#17250138
0"
#17291805
b10101 ,
1"
#17333472
0"
#17375139
b10110 ,
1"
#17416806
0"
#17458473
b10111 ,
1"
#17500140
0"
#17541807
b11000 ,
1"
#17583474
0"
#17625141
b11001 ,
1"
#17666808
0"
#17708475
b11010 ,
1"
#17750142
0"
#17791809
b11011 ,
1"
#17833476
0"
#17875143
b11100 ,
1"
#17916810
0"
#17958477
b11101 ,
1"
#18000144
0"
#18041811
b11110 ,
1"
#18083478
0"
#18125145
b11111 ,
1"
#18166812
0"
#18208479
b100000 ,
1"
#18250146
0"
#18291813
b100001 ,
1"
#18333480
0"
#18375147
b100010 ,
1"
#18416814
0"
#18458481
b100011 ,
1"
#18500148
0"
#18541815
b100100 ,
1"
#18583482
0"
#18625149
b100101 ,
1"
#18666816
0"
#18708483
b100110 ,
1"
#18750150
0"
#18791817
b100111 ,
1"
#18833484
0"
#18875151
b101000 ,
1"
#18916818
0"
#18958485
b101001 ,
1"
#19000152
0"
#19041819
b101010 ,
1"
#19083486
0"
#19125153
b101011 ,
1"
#19166820
0"
#19208487
b101100 ,
1"
#19250154
0"
#19291821
b101101 ,
1"
#19333488
0"
#19375155
b101110 ,
1"
#19416822
0"
#19458489
b101111 ,
1"
#19500156
0"
#19541823
b110000 ,
1"
#19583490
0"
#19625157
b110001 ,
1"
#19666824
0"
#19708491
b110010 ,
1"
#19750158
0"
#19791825
b110011 ,
1"
#19833492
0"
#19875159
b110100 ,
1"
#19916826
0"
#19958493
b110101 ,
1"
#20000160
0"
#20041827
b110110 ,
1"
#20083494
0"
#20125161
b110111 ,
1"
#20166828
0"
#20208495
b111000 ,
1"
#20250162
0"
#20291829
b111001 ,
1"
#20333496
0"
#20375163
b111010 ,
1"
#20416830
0"
#20458497
b111011 ,
1"
#20500164
0"
#20541831
b111100 ,
1"
#20583498
0"
#20625165
b111101 ,
1-
1"
#20666832
0"
#20708499
b111110 ,
1"
#20750166
0"
#20791833
b111111 ,
1"
#20833500
0"
#20875167
b1000000 ,
1"
#20916834
0"
#20958501
b1000001 ,
1"
#21000168
0"
#21041835
b1000010 ,
1"
#21083502
0"
#21125169
b1000011 ,
1"
#21166836
0"
#21208503
b1000100 ,
1"
#21250170
0"
#21291837
b1000101 ,
1"
#21333504
0"
#21375171
b1000110 ,
1"
#21416838
0"
#21458505
b1000111 ,
1"
#21500172
0"
#21541839
b1001000 ,
1"
#21583506
0"
#21625173
b1001001 ,
1"
#21666840
0"
#21708507
b1001010 ,
1"
#21750174
0"
#21791841
b1001011 ,
1"
#21833508
0"
#21875175
b1001100 ,
1"
#21916842
0"
#21958509
b1001101 ,
1"
#22000176
0"
#22041843
b1001110 ,
1"
#22083510
0"
#22125177
b1001111 ,
1"
#22166844
0"
#22208511
b1010000 ,
1"
#22250178
0"
#22291845
b1010001 ,
1"
#22333512
0"
#22375179
b1010010 ,
1"
#22416846
0"
#22458513
b1010011 ,
1"
#22500180
0"
#22541847
b1010100 ,
1"
#22583514
0"
#22625181
b1010101 ,
1"
#22666848
0"
#22708515
b1010110 ,
1"
#22750182
0"
#22791849
b1010111 ,
1"
#22833516
0"
#22875183
b1011000 ,
1"
#22916850
0"
#22958517
b1011001 ,
1"
#23000184
0"
#23041851
b1011010 ,
1"
#23083518
0"
#23125185
b1011011 ,
1"
#23166852
0"
#23208519
b1011100 ,
1"
#23250186
0"
#23291853
b1011101 ,
1"
#23333520
0"
#23375187
b1011110 ,
1"
#23416854
0"
#23458521
b1011111 ,
1"
#23500188
0"
#23541855
b1100000 ,
1"
#23583522
0"
#23625189
b1100001 ,
1"
#23666856
0"
#23708523
b1100010 ,
1"
#23750190
0"
#23791857
b1100011 ,
1"
#23833524
0"
#23875191
b1100100 ,
1"
#23916858
0"
#23958525
b1100101 ,
1"
#24000192
0"
#24041859
b1100110 ,
1"
#24083526
0"
#24125193
b1100111 ,
1"
#24166860
0"
#24208527
b1101000 ,
1"
#24250194
0"
#24291861
b1101001 ,
1"
#24333528
0"
#24375195
b1101010 ,
1"
#24416862
0"
#24458529
b1101011 ,
1"
#24500196
0"
#24541863
b1101100 ,
1"
#24583530
0"
#24625197
b1101101 ,
1"
#24666864
0"
#24708531
b1101110 ,
1"
#24750198
0"
#24791865
b1101111 ,
1"
#24833532
0"
#24875199
b1110000 ,
1"
#24916866
0"
#24958533
b1110001 ,
1"
#25000200
0"
#25041867
b1110010 ,
1"
#25083534
0"
#25125201
b1110011 ,
1"
#25166868
0"
#25208535
b1110100 ,
1"
#25250202
0"
#25291869
b1110101 ,
1"
#25333536
0"
#25375203
b1110110 ,
1"
#25416870
0"
#25458537
b1110111 ,
1"
#25500204
0"
#25541871
b1111000 ,
1"
#25583538
0"
#25625205
b1111001 ,
0-
1"
#25666872
0"
#25708539
b1111010 ,
1"
#25750206
0"
#25791873
b1111011 ,
1"
#25833540
0"
#25875207
b1111100 ,
1"
#25916874
0"
#25958541
b1111101 ,
1"
#26000208
0"
#26041875
b1111110 ,
1"
#26083542
0"
#26125209
b1111111 ,
1"
#26166876
0"
#26208543
b10000000 ,
1"
#26250210
0"
#26291877
b10000001 ,
1"
#26333544
0"
#26375211
b10000010 ,
1"
#26416878
0"
#26458545
b10000011 ,
1"
#26500212
0"
#26541879
b10000100 ,
1"
#26583546
0"
#26625213
b10000101 ,
1"
#26666880
0"
#26708547
b10000110 ,
1"
#26750214
0"
#26791881
b10000111 ,
1"
#26833548
0"
#26875215
b10001000 ,
1"
#26916882
0"
#26958549
b10001001 ,
1"
#27000216
0"
#27041883
b10001010 ,
1"
#27083550
0"
#27125217
b10001011 ,
1"
#27166884
0"
#27208551
b10001100 ,
1"
#27250218
0"
#27291885
b10001101 ,
1"
#27333552
0"
#27375219
b10001110 ,
1"
#27416886
0"
#27458553
b10001111 ,
1"
#27500220
0"
#27541887
b10010000 ,
1"
#27583554
0"
#27625221
b10010001 ,
1"
#27666888
0"
#27708555
b10010010 ,
1"
#27750222
0"
#27791889
b10010011 ,
1"
#27833556
0"
#27875223
b10010100 ,
1"
#27916890
0"
#27958557
b10010101 ,
1"
#28000224
0"
#28041891
b10010110 ,
1"
#28083558
0"
#28125225
b10010111 ,
1"
#28166892
0"
#28208559
b10011000 ,
1"
#28250226
0"
#28291893
b10011001 ,
1"
#28333560
0"
#28375227
b10011010 ,
1"
#28416894
0"
#28458561
b10011011 ,
1"
#28500228
0"
#28541895
b10011100 ,
1"
#28583562
0"
#28625229
b10011101 ,
1"
#28666896
0"
#28708563
b10011110 ,
1"
#28750230
0"
#28791897
b10011111 ,
1"
#28833564
0"
#28875231
b10100000 ,
1"
#28916898
0"
#28958565
b10100001 ,
1"
#29000232
0"
#29041899
b10100010 ,
1"
#29083566
0"
#29125233
b10100011 ,
1"
#29166900
0"
#29208567
b10100100 ,
1"
#29250234
0"
#29291901
b10100101 ,
1"
#29333568
0"
#29375235
b10100110 ,
1"
#29416902
0"
#29458569
b10100111 ,
1"
#29500236
0"
#29541903
b10101000 ,
1"
#29583570
0"
#29625237
b10101001 ,
1"
#29666904
0"
#29708571
b10101010 ,
1"
#29750238
0"
#29791905
b10101011 ,
1"
#29833572
0"
#29875239
b10101100 ,
1"
#29916906
0"
#29958573
b10101101 ,
1"
#30000240
0"
#30041907
b10101110 ,
1"
#30083574
0"
#30125241
b10101111 ,
1"
#30166908
0"
#30208575
b10110000 ,
1"
#30250242
0"
#30291909
b10110001 ,
1"
#30333576
0"
#30375243
b10110010 ,
1"
#30416910
0"
#30458577
b10110011 ,
1"
#30500244
0"
#30541911
b10110100 ,
1"
#30583578
0"
#30625245
b10110101 ,
1-
1"
#30666912
0"
#30708579
b10110110 ,
1"
#30750246
0"
#30791913
b10110111 ,
1"
#30833580
0"
#30875247
b10111000 ,
1"
#30916914
0"
#30958581
b10111001 ,
1"
#31000248
0"
#31041915
b10111010 ,
1"
#31083582
0"
#31125249
b10111011 ,
1"
#31166916
0"
#31208583
b10111100 ,
1"
#31250250
0"
#31291917
b10111101 ,
1"
#31333584
0"
#31375251
b10111110 ,
1"
#31416918
0"
#31458585
b10111111 ,
1"
#31500252
0"
#31541919
b11000000 ,
1"
#31583586
0"
#31625253
b11000001 ,
1"
#31666920
0"
#31708587
b11000010 ,
1"
#31750254
0"
#31791921
b11000011 ,
1"
#31833588
0"
#31875255
b11000100 ,
1"
#31916922
0"
#31958589
b11000101 ,
1"
#32000256
0"
#32041923
b11000110 ,
1"
#32083590
0"
#32125257
b11000111 ,
1"
#32166924
0"
#32208591
b11001000 ,
1"
#32250258
0"
#32291925
b11001001 ,
1"
#32333592
0"
#32375259
b11001010 ,
1"
#32416926
0"
#32458593
b11001011 ,
1"
#32500260
0"
#32541927
b11001100 ,
1"
#32583594
0"
#32625261
b11001101 ,
1"
#32666928
0"
#32708595
b11001110 ,
1"
#32750262
0"
#32791929
b11001111 ,
1"
#32833596
0"
#32875263
b11010000 ,
1"
#32916930
0"
#32958597
b11010001 ,
1"
#33000264
0"
#33041931
b11010010 ,
1"
#33083598
0"
#33125265
b11010011 ,
1"
#33166932
0"
#33208599
b11010100 ,
1"
#33250266
0"
#33291933
b11010101 ,
1"
#33333600
0"
#33375267
b11010110 ,
1"
#33416934
0"
#33458601
b11010111 ,
1"
#33500268
0"
#33541935
b11011000 ,
1"
#33583602
0"
#33625269
b11011001 ,
1"
#33666936
0"
#33708603
b11011010 ,
1"
#33750270
0"
#33791937
b11011011 ,
1"
#33833604
0"
#33875271
b11011100 ,
1"
#33916938
0"
#33958605
b11011101 ,
1"
#34000272
0"
#34041939
b11011110 ,
1"
#34083606
0"
#34125273
b11011111 ,
1"
#34166940
0"
#34208607
b11100000 ,
1"
#34250274
0"
#34291941
b11100001 ,
1"
#34333608
0"
#34375275
b11100010 ,
1"
#34416942
0"
#34458609
b11100011 ,
1"
#34500276
0"
#34541943
b11100100 ,
1"
#34583610
0"
#34625277
b11100101 ,
1"
#34666944
0"
#34708611
b11100110 ,
1"
#34750278
0"
#34791945
b11100111 ,
1"
#34833612
0"
#34875279
b11101000 ,
1"
#34916946
0"
#34958613
b11101001 ,
1"
#35000280
0"
#35041947
b11101010 ,
1"
#35083614
0"
#35125281
b11101011 ,
1"
#35166948
0"
#35208615
b11101100 ,
1"
#35250282
0"
#35291949
b11101101 ,
1"
#35333616
0"
#35375283
b11101110 ,
1"
#35416950
0"
#35458617
b11101111 ,
1"
#35500284
0"
#35541951
b11110000 ,
1"
#35583618
0"
#35625285
b11110001 ,
0-
1"
#35666952
0"
#35708619
b11110010 ,
1"
#35750286
0"
#35791953
b11110011 ,
1"
#35833620
0"
#35875287
b11110100 ,
1"
#35916954
0"
#35958621
b11110101 ,
1"
#36000288
0"
#36041955
b11110110 ,
0.
1"
#36083622
0"
#36125289
b11110111 ,
1"
#36166956
0"
#36208623
b11111000 ,
1"
#36250290
0"
#36291957
b11111001 ,
1"
#36333624
0"
#36375291
b11111010 ,
1"
#36416958
0"
#36458625
b11111011 ,
1"
#36500292
0"
#36541959
b11111100 ,
1"
#36583626
0"
#36625293
b11111101 ,
1"
#36666960
0"
#36708627
b11111110 ,
1"
#36750294
0"
#36791961
b11111111 ,
1"
#36833628
0"
#36875295
b100000000 ,
1"
#36916962
0"
#36958629
b100000001 ,
1"
#37000296
0"
#37041963
b100000010 ,
1"
#37083630
0"
#37125297
b100000011 ,
1"
#37166964
0"
#37208631
b100000100 ,
1"
#37250298
0"
#37291965
b100000101 ,
1"
#37333632
0"
#37375299
b100000110 ,
1"
#37416966
0"
#37458633
b100000111 ,
1"
#37500300
0"
#37541967
b100001000 ,
1"
#37583634
0"
#37625301
b100001001 ,
1"
#37666968
0"
#37708635
b100001010 ,
1"
#37750302
0"
#37791969
b100001011 ,
1"
#37833636
0"
#37875303
b100001100 ,
1"
#37916970
0"
#37958637
b100001101 ,
1"
#38000304
0"
#38041971
b100001110 ,
1"
#38083638
0"
#38125305
b100001111 ,
1"
#38166972
0"
#38208639
b100010000 ,
1"
#38250306
0"
#38291973
b100010001 ,
1"
#38333640
0"
#38375307
b100010010 ,
1"
#38416974
0"
#38458641
b100010011 ,
1"
#38500308
0"
#38541975
b100010100 ,
1"
#38583642
0"
#38625309
b100010101 ,
1"
#38666976
0"
#38708643
b100010110 ,
1"
#38750310
0"
#38791977
b100010111 ,
1"
#38833644
0"
#38875311
b100011000 ,
1"
#38916978
0"
#38958645
b100011001 ,
1"
#39000312
0"
#39041979
b100011010 ,
1"
#39083646
0"
#39125313
b100011011 ,
1"
#39166980
0"
#39208647
b100011100 ,
1"
#39250314
0"
#39291981
b100011101 ,
1"
#39333648
0"
#39375315
b100011110 ,
1"
#39416982
0"
#39458649
b100011111 ,
1"
#39500316
0"
#39541983
b100100000 ,
1"
#39583650
0"
#39625317
b100100001 ,
1"
#39666984
0"
#39708651
b100100010 ,
1"
#39750318
0"
#39791985
b100100011 ,
1"
#39833652
0"
#39875319
b100100100 ,
1"
#39916986
0"
#39958653
b100100101 ,
1"
#40000320
0"
#40041987
b100100110 ,
1"
#40083654
0"
#40125321
b100100111 ,
1"
#40166988
0"
#40208655
b100101000 ,
1"
#40250322
0"
#40291989
b100101001 ,
1"
#40333656
0"
#40375323
b100101010 ,
1"
#40416990
0"
#40458657
b100101011 ,
1"
#40500324
0"
#40541991
b100101100 ,
1"
#40583658
0"
#40625325
b100101101 ,
1-
1"
#40666992
0"
#40708659
b100101110 ,
1"
#40750326
0"
#40791993
b100101111 ,
1"
#40833660
0"
#40875327
b100110000 ,
1"
#40916994
0"
#40958661
b100110001 ,
1"
#41000328
0"
#41041995
b100110010 ,
1"
#41083662
0"
#41125329
b100110011 ,
1"
#41166996
0"
#41208663
b100110100 ,
1"
#41250330
0"
